instahunter/__init__.py
instahunter/lib/data.py
instahunter/lib/io.py
instahunter/lib/utils/question.py
instahunter/main.py
instahunter-2.0.4.dist-info/entry_points.txt
instahunter-2.0.4.dist-info/WHEEL
instahunter-2.0.4.dist-info/METADATA
instahunter-2.0.4.dist-info/RECORD
