Metadata-Version: 2.1
Name: instahunter
Version: 2.0.4
Summary: A CLI OSINT app that can fetch data from Instagram's Web API without the need of authentication.
Author: araekiel
Author-email: kumarshashwatsri@gmail.com
Requires-Python: >=3.8,<4.0
Classifier: Programming Language :: Python :: 3
Classifier: Programming Language :: Python :: 3.10
Classifier: Programming Language :: Python :: 3.8
Classifier: Programming Language :: Python :: 3.9
Requires-Dist: PyInquirer (>=1.0.3,<2.0.0)
Requires-Dist: pyfiglet (>=0.8.0,<0.9.0)
Requires-Dist: rich (==11.2.0)
